Metadata-Version: 2.2
Name: pixeloe
Version: 0.1.1
Summary: Detail-Oriented Pixelization based on Contrast-Aware Outline Expansion.
Author-email: "Shih-Ying Yeh(KohakuBlueLeaf)" <apolloyeh0123@gmail.com>
License: Apache License 2.0
Project-URL: Homepage, https://github.com/KohakuBlueleaf/PixelOE
Requires-Python: >=3.10
License-File: LICENSE
Requires-Dist: opencv-python
Requires-Dist: numpy
Requires-Dist: pillow
Requires-Dist: torch
Requires-Dist: kornia
